uptime_kuma_monitor.py
uptime_kuma_monitor-1.0.0.dist-info/LICENSE
uptime_kuma_monitor-1.0.0.dist-info/METADATA
uptime_kuma_monitor-1.0.0.dist-info/WHEEL
uptime_kuma_monitor-1.0.0.dist-info/top_level.txt
uptime_kuma_monitor-1.0.0.dist-info/RECORD
