Metadata-Version: 2.1
Name: uptime-kuma-monitor
Version: 1.0.0
Summary: Python wrapper around Uptime Kuma /metrics endpoint
Home-page: UNKNOWN
License: UNKNOWN
Platform: UNKNOWN
License-File: LICENSE
Requires-Dist: requests
Requires-Dist: prometheus-client
